README.txt
setup.cfg
setup.py
docs/HISTORY.txt
raptus/__init__.py
raptus.filesystemindex.egg-info/PKG-INFO
raptus.filesystemindex.egg-info/SOURCES.txt
raptus.filesystemindex.egg-info/dependency_links.txt
raptus.filesystemindex.egg-info/entry_points.txt
raptus.filesystemindex.egg-info/namespace_packages.txt
raptus.filesystemindex.egg-info/not-zip-safe
raptus.filesystemindex.egg-info/requires.txt
raptus.filesystemindex.egg-info/top_level.txt
raptus/filesystemindex/__init__.py
raptus/filesystemindex/config.py
raptus/filesystemindex/configure.zcml
raptus/filesystemindex/interfaces.py
raptus/filesystemindex/permissions.zcml
raptus/filesystemindex/browser/__init__.py
raptus/filesystemindex/browser/configure.zcml
raptus/filesystemindex/browser/filesystemindex_icon.gif
raptus/filesystemindex/browser/index.pt
raptus/filesystemindex/browser/index.py
raptus/filesystemindex/browser/list.pt
raptus/filesystemindex/browser/traverse.py
raptus/filesystemindex/browser/view.pt
raptus/filesystemindex/browser/view.py
raptus/filesystemindex/content/__init__.py
raptus/filesystemindex/content/configure.zcml
raptus/filesystemindex/content/filesystemindex.py
raptus/filesystemindex/i18n/raptus.filesystemindex-de.po
raptus/filesystemindex/i18n/raptus.filesystemindex.pot
raptus/filesystemindex/profiles/default/cssregistry.xml
raptus/filesystemindex/profiles/default/factorytool.xml
raptus/filesystemindex/profiles/default/metadata.xml
raptus/filesystemindex/profiles/default/rolemap.xml
raptus/filesystemindex/profiles/default/skins.xml
raptus/filesystemindex/profiles/default/types.xml
raptus/filesystemindex/profiles/default/types/FileSystemIndex.xml
raptus/filesystemindex/skins/raptus_filesystemindex/raptus_filesystemindex.css.dtml